FastExplain/__init__.py
FastExplain/main.py
FastExplain/PyALE/_ALE_generic.py
FastExplain/PyALE/__init__.py
FastExplain/PyALE/_src/ALE_1D.py
FastExplain/PyALE/_src/ALE_2D.py
FastExplain/PyALE/_src/__init__.py
FastExplain/PyALE/_src/lib.py
FastExplain/clean/__init__.py
FastExplain/clean/base.py
FastExplain/clean/dates.py
FastExplain/clean/encode_categorical.py
FastExplain/clean/fill_missing.py
FastExplain/clean/main.py
FastExplain/clean/shrink.py
FastExplain/clean/split.py
FastExplain/clustering/__init__.py
FastExplain/clustering/clustering.py
FastExplain/datasets/__init__.py
FastExplain/datasets/datasets.py
FastExplain/explain/__init__.py
FastExplain/explain/ale.py
FastExplain/explain/bin.py
FastExplain/explain/ebm.py
FastExplain/explain/importance.py
FastExplain/explain/main.py
FastExplain/explain/one_way.py
FastExplain/explain/pdp.py
FastExplain/explain/sensitivity.py
FastExplain/explain/shap.py
FastExplain/metrics/__init__.py
FastExplain/metrics/classification.py
FastExplain/metrics/regression.py
FastExplain/metrics/summary.py
FastExplain/models/__init__.py
FastExplain/models/base.py
FastExplain/models/classification.py
FastExplain/models/ebm.py
FastExplain/models/hypertuning.py
FastExplain/models/random_forest.py
FastExplain/models/regression.py
FastExplain/models/xgboost.py
FastExplain/models/algorithms/__init__.py
FastExplain/models/algorithms/ebm.py
FastExplain/models/algorithms/hypertuning.py
FastExplain/models/algorithms/params.py
FastExplain/models/algorithms/random_forest.py
FastExplain/models/algorithms/xgboost.py
FastExplain/utils/__init__.py
FastExplain/utils/colours.py
FastExplain/utils/data.py
FastExplain/utils/logic.py
FastExplain/utils/models.py
FastExplain/utils/plot.py
model_helper/__init__.py
model_helper/main.py
model_helper/PyALE/_ALE_generic.py
model_helper/PyALE/__init__.py
model_helper/PyALE/_src/ALE_1D.py
model_helper/PyALE/_src/ALE_2D.py
model_helper/PyALE/_src/__init__.py
model_helper/PyALE/_src/lib.py
model_helper/clean/__init__.py
fast_explain-0.0.91.dist-info/METADATA
fast_explain-0.0.91.dist-info/WHEEL
fast_explain-0.0.91.dist-info/top_level.txt
fast_explain-0.0.91.dist-info/RECORD
