Metadata-Version: 2.1
Name: fast-explain
Version: 0.0.91
Summary: Fit Fast, Explain Fast
Home-page: https://github.com/felixzhu17/FastExplain
Author: Felix Zhu
Author-email: zhu.felix@outlook.com
License: MIT
Platform: UNKNOWN
Requires-Dist: interpret
Requires-Dist: pandas
Requires-Dist: plotly
Requires-Dist: scikit-learn
Requires-Dist: scipy
Requires-Dist: plotly-express
Requires-Dist: xgboost
Requires-Dist: statsmodels
Requires-Dist: shap (==0.40.0)
Requires-Dist: numpy (==1.21)
Requires-Dist: pytest
Requires-Dist: hyperopt
Requires-Dist: setuptools-git
Requires-Dist: tornado (==5.1)
